tversky_neural_network/__init__.py
tversky_neural_network/tversky_neural_network.py
tversky_neural_network_pytorch-0.0.2.dist-info/WHEEL
tversky_neural_network_pytorch-0.0.2.dist-info/METADATA
tversky_neural_network_pytorch-0.0.2.dist-info/RECORD
