Metadata-Version: 2.4
Name: tversky-neural-network-pytorch
Version: 0.0.2
Summary: Tversky Neural Network
Keywords: artificial intelligence,deep learning,tversky similarity,psychologically plausible,neural networks
Author: Tarek Liu
Author-email: Tarek Liu <liuyuwei.tarek@gmail.com>
License-Expression: MIT
Classifier: Development Status :: 4 - Beta
Classifier: Intended Audience :: Developers
Classifier: Topic :: Scientific/Engineering :: Artificial Intelligence
Classifier: Programming Language :: Python :: 3.10
Requires-Dist: numpy==1.26.4
Requires-Dist: torch==2.1.2
Requires-Dist: pytest ; extra == 'test'
Requires-Python: >=3.10
Project-URL: Homepage, https://pypi.org/project/tversky-neural-network-pytorch/
Project-URL: Repository, https://github.com/liuyuweitarek/tversky-neural-network-pytorch
Provides-Extra: examples
Provides-Extra: test
